umt_python/__init__.py
umt_python/delete_spaces.py
umt_python/format_string.py
umt_python/from_base64.py
umt_python/has_no_letters.py
umt_python/pad_end.py
umt_python/pad_start.py
umt_python/random_string.py
umt_python/random_string_initialization.py
umt_python/reverse_string.py
umt_python/to_base64.py
umt_python/to_half_width.py
umt_python/trim_characters.py
umt_python/trim_end_characters.py
umt_python/trim_start_characters.py
umt_python-0.1.1.dist-info/licenses/LICENSE
umt_python-0.1.1.dist-info/METADATA
umt_python-0.1.1.dist-info/WHEEL
umt_python-0.1.1.dist-info/top_level.txt
umt_python-0.1.1.dist-info/RECORD
