Metadata-Version: 2.4
Name: umt_python
Version: 0.1.1
Summary: A collection of useful utility functions for various tasks in Python, focusing on string manipulation and formatting.
Author-email: riya-amemiya <riyaamemiya@gmail.com>
License-Expression: MIT
Project-URL: Bug Tracker, https://github.com/riya-amemiya/UMT/issues
Project-URL: Homepage, https://github.com/riya-amemiya/UMT
Project-URL: Repository, https://github.com/riya-amemiya/UMT
Classifier: Programming Language :: Python :: 3
Classifier: Programming Language :: Python :: 3.9
Classifier: Programming Language :: Python :: 3.10
Classifier: Programming Language :: Python :: 3.11
Classifier: Programming Language :: Python :: 3.12
Classifier: Operating System :: OS Independent
Classifier: Topic :: Software Development :: Libraries :: Python Modules
Classifier: Topic :: Utilities
Requires-Python: >=3.9
License-File: LICENSE
Dynamic: license-file
